MANIFEST.in
setup.py
calresa/__init__.py
calresa/calendar.py
calresa/roomstate.py
calresa/state.py
calresa/views.py
calresa.egg-info/PKG-INFO
calresa.egg-info/SOURCES.txt
calresa.egg-info/dependency_links.txt
calresa.egg-info/not-zip-safe
calresa.egg-info/requires.txt
calresa.egg-info/top_level.txt
calresa/static/style.css
calresa/templates/base.xhtml
calresa/templates/booking_view.xhtml
calresa/templates/calendar.xhtml
calresa/templates/room_selection.xhtml