Metadata-Version: 1.1
Name: calresa
Version: 0.1
Summary: Room booking viewer
Home-page: https://github.com/ProgVal/Calresa
Author: Valentin Lorentz
Author-email: progval+calresa@progval.net
License: UNKNOWN
Platform: UNKNOWN
Classifier: Development Status :: 3 - Alpha
Classifier: Environment :: Web Environment
Classifier: Framework :: Flask
Classifier: Intended Audience :: End Users/Desktop
Classifier: License :: OSI Approved :: MIT License
Classifier: Natural Language :: English
Classifier: Natural Language :: French
Classifier: Operating System :: OS Independent
Classifier: Programming Language :: Python :: 3
Classifier: Topic :: Office/Business :: Scheduling
